eagle_gateway.py
iotrelay_eagle-1.0.2.dist-info/DESCRIPTION.rst
iotrelay_eagle-1.0.2.dist-info/METADATA
iotrelay_eagle-1.0.2.dist-info/RECORD
iotrelay_eagle-1.0.2.dist-info/WHEEL
iotrelay_eagle-1.0.2.dist-info/entry_points.txt
iotrelay_eagle-1.0.2.dist-info/metadata.json
iotrelay_eagle-1.0.2.dist-info/top_level.txt
