Metadata-Version: 2.0
Name: iotrelay-eagle
Version: 1.0.2
Summary: IoT Relay plugin for the Eagle™ Home Energy Gateway
Home-page: https://github.com/eman/iotrelay-eagle
Author: Emmanuel Levijarvi
Author-email: emansl@gmail.com
License: BSD
Keywords: Eagle Energy Gateway IoT electricity
Platform: UNKNOWN
Classifier: Development Status :: 4 - Beta
Classifier: Intended Audience :: Developers
Classifier: Topic :: Utilities
Classifier: License :: OSI Approved :: BSD License
Classifier: Operating System :: OS Independent
Classifier: Programming Language :: Python :: 2
Classifier: Programming Language :: Python :: 3
Requires-Dist: iotrelay
Requires-Dist: meter-reader
